DialogsPlus/__init__.py
DialogsPlus/dialogsplus.py
DialogsPlus/py.typed
DialogsPlus/utils/config.py
DialogsPlus/widgets/base.py
DialogsPlus/widgets/styling.py
DialogsPlus/widgets/wrappers.py
DialogsPlus/widgets/assets/robot.ico
robotframework_dialogsplus-0.1.1.dist-info/METADATA
robotframework_dialogsplus-0.1.1.dist-info/WHEEL
robotframework_dialogsplus-0.1.1.dist-info/RECORD
