Metadata-Version: 2.4
Name: robotframework-dialogsplus
Version: 0.1.1
Summary: A drop-in enhancement for Robot Framework's Dialogs library with modern UI and extended user interaction keywords.
Author-email: Alpha-Centauri-00 <Alpha@Centauri.c0m>
License-Expression: MIT
Requires-Python: >=3.10
Requires-Dist: customtkinter>=5.2.2
Requires-Dist: pyyaml>=6.0.3
Requires-Dist: robotframework>=7.3.2
